fetoflow/__init__.py
fetoflow/bc_utils.py
fetoflow/file_parsing_utils.py
fetoflow/geometry_utils.py
fetoflow/helper_functions.py
fetoflow/matrix_builder.py
fetoflow/pressure_flow_utils.py
fetoflow/resistance_utils.py
fetoflow/solve_utils.py
fetoflow-0.1.3.dist-info/licenses/LICENSE
fetoflow-0.1.3.dist-info/METADATA
fetoflow-0.1.3.dist-info/WHEEL
fetoflow-0.1.3.dist-info/top_level.txt
fetoflow-0.1.3.dist-info/RECORD
